<?xml version="1.0" encoding="UTF-8" ?>
<!DOCTYPE sqlMap PUBLIC "-//ibatis.apache.org//DTD SQL Map 2.0//EN" "http://ibatis.apache.org/dtd/sql-map-2.dtd" >
<sqlMap namespace="cn.com.kxcomm.entity.PriceOverviewEntity">
  	<resultMap id="PriceOverviewResultMap" class="cn.com.kxcomm.entity.PriceOverviewEntity">
		<result column="id" property="id" jdbcType="BIGINT" />
		<result column="tb_product_id" property="tbProductId" jdbcType="BIGINT" />
		<result column="config_name" property="configName" jdbcType="VARCHAR" />
		<result column="type" property="type" jdbcType="SMALLINT" />
		<result column="pre_month_price" property="preMonthPrice" jdbcType="DOUBLE" />
		<result column="pre_year_price" property="PreYearPrice" jdbcType="DOUBLE" />
	</resultMap>

	<select id="queryAll" resultMap="PriceOverviewResultMap">
		select id,tb_product_id from tb_price_overview
   </select>
  
</sqlMap>