<?xml version="1.0"?>
<!DOCTYPE hibernate-mapping PUBLIC "-//Hibernate/Hibernate Mapping DTD 3.0//EN"
"http://hibernate.sourceforge.net/hibernate-mapping-3.0.dtd">
<!-- 
    Mapping file autogenerated by MyEclipse - Hibernate Tools
-->
<hibernate-mapping>
    <class name="com.shengdai.kpi.system.org.vo.Position" table="SYS_POSITION" where="flg_deleted=0">
    	<cache usage="nonstrict-read-write" />
        <id name="id" type="java.lang.String">
            <column name="ID" length="32" />
            <generator class="uuid.hex"></generator>
        </id>
        <many-to-one name="org" class="com.shengdai.kpi.system.org.vo.Org" fetch="select">
            <column name="ORG_ID" length="32" not-null="true" />
        </many-to-one>
        <property name="orgName" type="java.lang.String">
            <column name="ORG_NAME" length="100" />
        </property>
        <property name="positionName" type="java.lang.String">
            <column name="POSITION_NAME" length="100" />
        </property>
        <property name="oldOrgId" type="string" update="false" insert="false">
            <column name="ORG_ID" length="1000" />
        </property>
         <property name="remark" type="java.lang.String">
            <column name="REMARK" length="1000" />
        </property>
        <property name="flgDeleted" type="int">
            <column name="FLG_DELETED" />
        </property>
        <property name="priority" type="int">
            <column name="PRIORITY" />
        </property>
        <set name="user" inverse="false"  lazy="true"  where="flg_deleted=0">
        	<cache usage="nonstrict-read-write" />
        	<key>
        		<column name="POSITION_ID" length="32"></column>
        	</key>
        	<one-to-many class="com.shengdai.kpi.system.org.vo.User"/>
        </set>
    </class>
</hibernate-mapping>
