<?xml version="1.0" encoding="utf-8"?>
<!DOCTYPE hibernate-mapping PUBLIC "-//Hibernate/Hibernate Mapping DTD 3.0//EN"
                                   "http://hibernate.sourceforge.net/hibernate-mapping-3.0.dtd">
<!-- 
    Mapping file autogenerated by MyEclipse Persistence Tools
-->
<hibernate-mapping>
 <class name="com.shengdai.kpi.yearplan.vo.YearPlanIndicator"
  schema="KPICCS" select-before-update="true"
  table="YEAR_PLAN_INDICATOR" where="flg_deleted=0">
  <id name="id" type="java.lang.String">
   <column length="32" name="ID"/>
   <generator class="uuid.hex"/>
  </id>
  <property generated="never" lazy="false" name="name" type="java.lang.String">
   <column length="100" name="NAME"/>
  </property>
  <property generated="never" lazy="false" name="baseValue" type="java.lang.String">
   <column length="2000" name="BASE_VALUE"/>
  </property>
  <property generated="never" lazy="false" name="defyValue" type="java.lang.String">
   <column length="2000" name="DEFY_VALUE"/>
  </property>
  <property generated="never" lazy="false" name="quantized" type="integer">
   <column name="ISQUANTIZED" precision="22" scale="0"/>
  </property>
  <property generated="never" lazy="false" name="calWay" type="java.lang.String">
   <column length="2000" name="CAL_WAY"/>
  </property>
  <property generated="never" lazy="false" name="dateSource" type="java.lang.String">
   <column length="2000" name="DATE_SOURCES"/>
  </property>
  <property generated="never" lazy="false" name="scale" type="integer">
   <column name="SCALE" precision="22" scale="0"/>
  </property>
  <property generated="never" lazy="false" name="priority" type="integer">
   <column name="PRIORITY" precision="22" scale="0"/>
  </property>
  <property generated="never" lazy="false" name="remark" type="java.lang.String">
   <column length="2000" name="REMARK"/>
  </property>
  <property generated="never" lazy="false" name="assWay" type="java.lang.String">
   <column length="2000" name="ASS_WAY"/>
  </property>
  <property generated="never" lazy="false" name="defined" type="java.lang.String">
   <column length="2000" name="DEFINED"/>
  </property>
  <property generated="never" lazy="false" name="refResourceId" type="java.lang.String">
   <column length="32" name="REF_RESOURCE_ID"/>
  </property>
  <property generated="never" lazy="false" name="refResourceClass" type="java.lang.String">
   <column length="100" name="REF_RESOURCE_CLASS"/>
  </property>
  <property generated="never" lazy="false" name="srcIndicatorId" type="java.lang.String">
   <column length="32" name="SRC_INDICATOR_ID"/>
  </property>
  <property generated="never" lazy="false" name="standard" type="java.lang.String">
   <column length="2000" name="STANDARD"/>
  </property>
  <property generated="never" lazy="false" name="assOrgName" type="java.lang.String">
   <column length="500" name="ASS_ORG_NAME"/>
  </property>
  <many-to-one class="com.shengdai.kpi.yearplan.vo.YearPlanIndicatorType"
   fetch="select" name="yearPlanIndicatorType">
   <column length="32" name="INDICATOR_TYPE_ID"/>
  </many-to-one><!--
  <set cascade="all,delete-orphan" name="handlerDetails" sort="unsorted">
   <key>
    <column length="32" name="YEAR_PLAN_INDICATOR_ID"/>
   </key>
   <one-to-many class="com.shengdai.kpi.yearplan.vo.YearPlanIndiNodeHandlerDetail"/>
  </set>
  --><property generated="never" lazy="false" name="flgDeleted" type="integer">
   <column name="FLG_DELETED"/>
  </property>
  <many-to-one class="com.shengdai.kpi.yearplan.vo.YearPlan" name="yearPlan">
   <column name="YEAR_PLAN_ID"/>
  </many-to-one>
 </class>
</hibernate-mapping>
